{
    "assessmentData": [{
            "id": "1",
            "question_text": "Зеленый пигмент в растениях, который поглощает солнечный свет и превращает его в энергию для «кормления» растения, называется:",
            "question_type": "radio",
            "answers": [{
                "id": "1",
                "answer_text": "Хлорофилл",
                "is_correct": 1,
                "feedback": "Да, это безусловный двигатель командной работы."
            }, {
                "id": "2",
                "answer_text": "Митохондрион",
                "is_correct": 0,
                "feedback": "Это поможет и со стрессом справиться, и в коллектив влиться. "
            }]
        },
        {
            "id": "2",
            "question_text": "Наше солнце является:",
            "question_type": "radio",
            "answers": [{
                "id": "1",
                "answer_text": "Звездой",
                "is_correct": 1,
                "feedback": "Да, это безусловный двигатель командной работы."
            }, {
                "id": "2",
                "answer_text": "Планетой",
                "is_correct": 0,
                "feedback": "Это поможет и со стрессом справиться, и в коллектив влиться. "
            }]
        },
        {
            "id": "3",
            "question_text": "Сколько костей имеет средний взрослый человек?",
            "question_type": "radio",
            "answers": [{
                "id": "1",
                "answer_text": "508-510",
                "is_correct": 0,
                "feedback": "Да, это безусловный двигатель командной работы."
            }, {
                "id": "2",
                "answer_text": "205-208",
                "is_correct": 1,
                "feedback": "Это поможет и со стрессом справиться, и в коллектив влиться. "
            }]
        },
        {
            "id": "4",
            "question_text": "Процесс превращения жидкости в газ называется:",
            "question_type": "radio",
            "answers": [{
                "id": "1",
                "answer_text": "Испарение",
                "is_correct": 1,
                "feedback": "Да, это безусловный двигатель командной работы."
            }, {
                "id": "2",
                "answer_text": "Конденсация",
                "is_correct": 0,
                "feedback": "Это поможет и со стрессом справиться, и в коллектив влиться. "
            }]
        },
        {
            "id": "5",
            "question_text": "Моллюск является примером:",
            "question_type": "radio",
            "answers": [{
                "id": "1",
                "answer_text": "Позвоночных",
                "is_correct": 0,
                "feedback": "Да, это безусловный двигатель командной работы."
            }, {
                "id": "2",
                "answer_text": "Беспозвоночных",
                "is_correct": 1,
                "feedback": "Это поможет и со стрессом справиться, и в коллектив влиться. "
            }]
        },
        {
            "id": "6",
            "question_text": "Часть земли, которую мы видим, называется:",
            "question_type": "radio",
            "answers": [{
                "id": "1",
                "answer_text": "Кора",
                "is_correct": 1,
                "feedback": "Да, это безусловный двигатель командной работы."
            }, {
                "id": "2",
                "answer_text": "Мантия",
                "is_correct": 0,
                "feedback": "Это поможет и со стрессом справиться, и в коллектив влиться. "
            }]
        },
        {
            "id": "7",
            "question_text": "Что НЕ является частью системы кровообращения?",
            "question_type": "radio",
            "answers": [{
                "id": "1",
                "answer_text": "Желудок",
                "is_correct": 1,
                "feedback": "Да, это безусловный двигатель командной работы."
            },{
                "id": "2",
                "answer_text": "Артерии",
                "is_correct": 0,
                "feedback": "Это поможет и со стрессом справиться, и в коллектив влиться. "
            },{
                "id": "3",
                "answer_text": "Вены",
                "is_correct": 0,
                "feedback": "Это поможет и со стрессом справиться, и в коллектив влиться. "
            },{
                "id": "4",
                "answer_text": "Сердце",
                "is_correct": 0,
                "feedback": "Это поможет и со стрессом справиться, и в коллектив влиться. "
            }]
        },
        {
            "id": "8",
            "question_text": "Сколько камер имеет человеческое сердце?",
            "question_type": "radio",
            "answers": [{
                "id": "1",
                "answer_text": "4",
                "is_correct": 1,
                "feedback": "Да, это безусловный двигатель командной работы."
            }, {
                "id": "2",
                "answer_text": "5",
                "is_correct": 0,
                "feedback": "Это поможет и со стрессом справиться, и в коллектив влиться. "
            }]
        },
        {
            "id": "9",
            "question_text": "Процесс разрушения скалы ветром или водой называется:",
            "question_type": "radio",
            "answers": [{
                "id": "1",
                "answer_text": "Эрозия",
                "is_correct": 1,
                "feedback": "Да, это безусловный двигатель командной работы."
            }, {
                "id": "2",
                "answer_text": "Имплозия",
                "is_correct": 0,
                "feedback": "Это поможет и со стрессом справиться, и в коллектив влиться. "
            }]
        },
        {
            "id": "10",
            "question_text": "Галактика, ближайшая к нашей, называется ...",
            "question_type": "radio",
            "answers": [{
                "id": "1",
                "answer_text": "Андромеда",
                "is_correct": 1,
                "feedback": "Да, это безусловный двигатель командной работы."
            }, {
                "id": "2",
                "answer_text": "Орион",
                "is_correct": 0,
                "feedback": "Это поможет и со стрессом справиться, и в коллектив влиться. "
            }]
        }
    ]
}
